<?xml version="1.0" encoding="UTF-8"?>
<ExchangePlanContent xmlns="http://v8.1c.ru/8.3/xcf/extrnprops" xmlns:xr="http://v8.1c.ru/8.3/xcf/readable" xmlns:xs="http://www.w3.org/2001/XMLSchema" xmlns:xsi="http://www.w3.org/2001/XMLSchema-instance" version="2.18">
	<Item>
		<Metadata>InformationRegister.ТК_РегистрацияВыгрузкиЗКС</Metadata>
		<AutoRecord>Deny</AutoRecord>
	</Item>
	<Item>
		<Metadata>Document.ТК_НалоговаяНакладная</Metadata>
		<AutoRecord>Deny</AutoRecord>
	</Item>
	<Item>
		<Metadata>Document.СчетНаОплату</Metadata>
		<AutoRecord>Deny</AutoRecord>
	</Item>
	<Item>
		<Metadata>Document.КонсолидированныеОстаткиОрганизации</Metadata>
		<AutoRecord>Deny</AutoRecord>
	</Item>
	<Item>
		<Metadata>Document.ТК_ЗакрытиеСменыЗКС</Metadata>
		<AutoRecord>Deny</AutoRecord>
	</Item>
	<Item>
		<Metadata>Document.ВозвратПоставщику</Metadata>
		<AutoRecord>Deny</AutoRecord>
	</Item>
	<Item>
		<Metadata>Document.ТК_КорректировкаДолга</Metadata>
		<AutoRecord>Deny</AutoRecord>
	</Item>
	<Item>
		<Metadata>Document.ТК_Приложение2КНалоговойНакладной</Metadata>
		<AutoRecord>Deny</AutoRecord>
	</Item>
	<Item>
		<Metadata>Document.РеализацияТоваров</Metadata>
		<AutoRecord>Deny</AutoRecord>
	</Item>
	<Item>
		<Metadata>Document.ПоступлениеТоваров</Metadata>
		<AutoRecord>Deny</AutoRecord>
	</Item>
	<Item>
		<Metadata>Document.ВыпускПродукции</Metadata>
		<AutoRecord>Deny</AutoRecord>
	</Item>
	<Item>
		<Metadata>Document.РасходныйКассовыйОрдер</Metadata>
		<AutoRecord>Deny</AutoRecord>
	</Item>
	<Item>
		<Metadata>Document.ВозвратОтПокупателя</Metadata>
		<AutoRecord>Deny</AutoRecord>
	</Item>
</ExchangePlanContent>